blockdiagram/__init__.py
blockdiagram/blockdiagram.py
blockdiagram-0.1.0.data/scripts/blockdiagram.py
blockdiagram-0.1.0.dist-info/LICENSE.txt
blockdiagram-0.1.0.dist-info/METADATA
blockdiagram-0.1.0.dist-info/WHEEL
blockdiagram-0.1.0.dist-info/top_level.txt
blockdiagram-0.1.0.dist-info/RECORD
