Metadata-Version: 2.1
Name: blockdiagram
Version: 0.1.0
Summary: Module for creating block diagrams and other three-dimensional displays from stratigraphic models
Home-page: https://github.com/zsylvester/blockdiagram
Author: Zoltan Sylvester
Author-email: zoltan.sylvester@beg.utexas.edu
License: UNKNOWN
Keywords: geomorphology,stratigraphy,3D visualization
Platform: UNKNOWN
Classifier: Programming Language :: Python :: 2
Classifier: Programming Language :: Python :: 3
Classifier: Intended Audience :: Science/Research
Classifier: License :: OSI Approved :: Apache Software License
Classifier: Operating System :: OS Independent
Requires-Dist: numpy
Requires-Dist: matplotlib
Requires-Dist: mayavi
Requires-Dist: scipy
Requires-Dist: pillow
